<annotation>
	<folder>JPEGImages</folder>
	<filename>Anime_42.jpg</filename>
	<path>D:\VOC_2018_12_6\JPEGImages\Anime_42.jpg</path>
	<source>
		<database>Unknown</database>
	</source>
	<size>
		<width>640</width>
		<height>945</height>
		<depth>3</depth>
	</size>
	<segmented>0</segmented>
	<object>
		<name>anime face</name>
		<pose>Unspecified</pose>
		<truncated>0</truncated>
		<difficult>0</difficult>
		<bndbox>
			<xmin>173</xmin>
			<ymin>182</ymin>
			<xmax>402</xmax>
			<ymax>385</ymax>
		</bndbox>
	</object>
</annotation>
